{
  "parent": "mineprotocol:first_fishing",
  "criteria": {
    "ookatuo": {
      "conditions": {
        "item": {
          "items": [
            "mineprotocol:ookatuo"
          ]
        }
      },
      "trigger": "minecraft:fishing_rod_hooked"
    }
  },
  "display": {
    "announce_to_chat": true,
    "description": {
      "translate": "advancements.mineprotocol.get_ookatuo.desc"
    },
    "frame": "challenge",
    "hidden": true,
    "icon": {
      "item": "mineprotocol:ookatuo",
      "nbt": "{Damage:0}"
    },
    "show_toast": true,
    "title": {
      "translate": "advancements.mineprotocol.get_ookatuo.title"
    }
  },
  "sends_telemetry_event": true
}